apicaller/__init__.py
apicaller/base.py
apicaller/openai_caller.py
apicaller/parser.py
apicaller/swagger.py
pyapicaller-0.2.2.dist-info/LICENSE
pyapicaller-0.2.2.dist-info/METADATA
pyapicaller-0.2.2.dist-info/WHEEL
pyapicaller-0.2.2.dist-info/top_level.txt
pyapicaller-0.2.2.dist-info/RECORD
