Metadata-Version: 2.2
Name: pyapicaller
Version: 0.2.2
Summary: Easily connect any API to OpenAI function calling
Author-email: Roman Medvedev <pypi@romavm.dev>
License: MIT
Project-URL: homepage, https://github.com/Romamo/pyapicaller
Keywords: API,caller,Python
Classifier: Development Status :: 3 - Alpha
Classifier: Intended Audience :: Developers
Classifier: Programming Language :: Python :: 3
Classifier: License :: OSI Approved :: MIT License
Classifier: Operating System :: OS Independent
Classifier: Topic :: Software Development :: Libraries :: Python Modules
Requires-Python: >=3.9
License-File: LICENSE
Requires-Dist: jsonref
Provides-Extra: yaml
Requires-Dist: pyyaml; extra == "yaml"
Provides-Extra: swagger
Requires-Dist: urllib3>=1.15; extra == "swagger"
Requires-Dist: six>=1.10; extra == "swagger"
Requires-Dist: certifi; extra == "swagger"
Requires-Dist: python-dateutil; extra == "swagger"
Provides-Extra: openai
Requires-Dist: openai; extra == "openai"
